fid_mcp/__init__.py
fid_mcp/config.py
fid_mcp/server.py
fid_mcp/shell.py
fid_mcp-0.1.2.dist-info/METADATA
fid_mcp-0.1.2.dist-info/WHEEL
fid_mcp-0.1.2.dist-info/entry_points.txt
fid_mcp-0.1.2.dist-info/licenses/LICENSE
fid_mcp-0.1.2.dist-info/RECORD
