Metadata-Version: 2.4
Name: fid-mcp
Version: 0.1.2
Summary: MCP Server for serving configurable Fid toolkits
Project-URL: Homepage, https://fidlabs.ai
Author-email: Fid Labs <contact@fidlabs.ai>
License-Expression: LicenseRef-Proprietary
License-File: LICENSE
Keywords: mcp,model-context-protocol,server,tools
Classifier: Operating System :: OS Independent
Classifier: Programming Language :: Python :: 3
Requires-Python: >=3.8
Requires-Dist: aiohttp
Requires-Dist: mcp
Requires-Dist: pexpect
Requires-Dist: pydantic
